odoo/addons/fs_product_multi_image/README.rst
odoo/addons/fs_product_multi_image/__init__.py
odoo/addons/fs_product_multi_image/__manifest__.py
odoo/addons/fs_product_multi_image/i18n/es.po
odoo/addons/fs_product_multi_image/i18n/fr.po
odoo/addons/fs_product_multi_image/i18n/fs_product_multi_image.pot
odoo/addons/fs_product_multi_image/i18n/it.po
odoo/addons/fs_product_multi_image/models/__init__.py
odoo/addons/fs_product_multi_image/models/fs_product_category_image.py
odoo/addons/fs_product_multi_image/models/fs_product_image.py
odoo/addons/fs_product_multi_image/models/image_tag.py
odoo/addons/fs_product_multi_image/models/product_category.py
odoo/addons/fs_product_multi_image/models/product_product.py
odoo/addons/fs_product_multi_image/models/product_template.py
odoo/addons/fs_product_multi_image/models/product_template_attribute_line.py
odoo/addons/fs_product_multi_image/readme/CONTRIBUTORS.md
odoo/addons/fs_product_multi_image/readme/DESCRIPTION.md
odoo/addons/fs_product_multi_image/readme/HISTORY.md
odoo/addons/fs_product_multi_image/readme/USAGE.md
odoo/addons/fs_product_multi_image/readme/newsfragments/.gitignore
odoo/addons/fs_product_multi_image/security/fs_product_category_image.xml
odoo/addons/fs_product_multi_image/security/fs_product_image.xml
odoo/addons/fs_product_multi_image/static/description/icon.png
odoo/addons/fs_product_multi_image/static/description/index.html
odoo/addons/fs_product_multi_image/tests/__init__.py
odoo/addons/fs_product_multi_image/tests/test_fs_product_multi_image.py
odoo/addons/fs_product_multi_image/views/fs_product_category_image.xml
odoo/addons/fs_product_multi_image/views/fs_product_image.xml
odoo/addons/fs_product_multi_image/views/image_tag.xml
odoo/addons/fs_product_multi_image/views/product_category.xml
odoo/addons/fs_product_multi_image/views/product_product.xml
odoo/addons/fs_product_multi_image/views/product_template.xml
odoo_addon_fs_product_multi_image-17.0.1.0.1.1.dist-info/METADATA
odoo_addon_fs_product_multi_image-17.0.1.0.1.1.dist-info/WHEEL
odoo_addon_fs_product_multi_image-17.0.1.0.1.1.dist-info/top_level.txt
odoo_addon_fs_product_multi_image-17.0.1.0.1.1.dist-info/RECORD
