Metadata-Version: 2.1
Name: odoo-addon-fs_product_multi_image
Version: 17.0.1.0.1.1
Requires-Python: >=3.10
Requires-Dist: odoo-addon-fs_base_multi_image>=17.0dev,<17.1dev
Requires-Dist: odoo-addon-image_tag>=17.0dev,<17.1dev
Requires-Dist: odoo>=17.0a,<17.1dev
Summary: Manage multi images from extenal file system on product
Home-page: https://github.com/OCA/storage
License: AGPL-3
Author: ACSONE SA/NV,Odoo Community Association (OCA)
Author-email: support@odoo-community.org
Classifier: Programming Language :: Python
Classifier: Framework :: Odoo
Classifier: Framework :: Odoo :: 17.0
Classifier: License :: OSI Approved :: GNU Affero General Public License v3
Classifier: Development Status :: 3 - Alpha
